treevizer/__init__.py
treevizer/config.py
treevizer/main.py
treevizer/builders/__init__.py
treevizer/builders/balanced_binary_tree.py
treevizer/builders/base_graph.py
treevizer/builders/edge.py
treevizer/builders/linked_list.py
treevizer/builders/recursion.py
treevizer/builders/trie.py
treevizer/builders/vertex.py
treevizer/exporters/__init__.py
treevizer/exporters/dot.py
treevizer/exporters/gif.py
treevizer/exporters/png.py
treevizer/exporters/utils.py
treevizer-0.2.5.dist-info/LICENSE
treevizer-0.2.5.dist-info/METADATA
treevizer-0.2.5.dist-info/WHEEL
treevizer-0.2.5.dist-info/top_level.txt
treevizer-0.2.5.dist-info/RECORD
