Metadata-Version: 2.1
Name: treevizer
Version: 0.2.5
Summary: A graph visualization tool
Home-page: https://github.com/andreasarne/treeviz
Author: Andreas Arnesson
Author-email: aar@bth.se
Classifier: Programming Language :: Python :: 3.7
Classifier: Programming Language :: Python :: 3.8
Classifier: Programming Language :: Python :: 3.9
Classifier: Programming Language :: Python :: 3.10
Classifier: Intended Audience :: Education
Classifier: License :: OSI Approved :: MIT License
Classifier: Operating System :: OS Independent
Requires-Python: >=3.7
License-File: LICENSE
Requires-Dist: Pillow (~=10.4) ; sys_platform != "cygwin"
